vero_sdk/__init__.py
vero_sdk/_version.cpython-39-x86_64-linux-gnu.so
vero_sdk/_version.py
vero_sdk/api_server.cpython-39-x86_64-linux-gnu.so
vero_sdk/api_server.py
vero_sdk/client.cpython-39-x86_64-linux-gnu.so
vero_sdk/client.py
vero_sdk/config.cpython-39-x86_64-linux-gnu.so
vero_sdk/config.py
vero_sdk/core.cpython-39-x86_64-linux-gnu.so
vero_sdk/core.py
vero_sdk/backtest/__init__.py
vero_sdk/backtest/client.cpython-39-x86_64-linux-gnu.so
vero_sdk/backtest/client.py
vero_sdk/backtest/engine.cpython-39-x86_64-linux-gnu.so
vero_sdk/backtest/engine.py
vero_sdk/backtest/metrics.cpython-39-x86_64-linux-gnu.so
vero_sdk/backtest/metrics.py
vero_sdk/backtest/report.cpython-39-x86_64-linux-gnu.so
vero_sdk/backtest/report.py
vero_sdk/backtest/settings.cpython-39-x86_64-linux-gnu.so
vero_sdk/backtest/settings.py
vero_sdk/features/__init__.py
vero_sdk/features/indicators.cpython-39-x86_64-linux-gnu.so
vero_sdk/features/indicators.py
vero_sdk/features/market_data.cpython-39-x86_64-linux-gnu.so
vero_sdk/features/market_data.py
vero_sdk/features/orders.cpython-39-x86_64-linux-gnu.so
vero_sdk/features/orders.py
vero_sdk/features/streaming.cpython-39-x86_64-linux-gnu.so
vero_sdk/features/streaming.py
vero_sdk/risk/__init__.py
vero_sdk/risk/manager.cpython-39-x86_64-linux-gnu.so
vero_sdk/risk/manager.py
vero_sdk/risk/rules.cpython-39-x86_64-linux-gnu.so
vero_sdk/risk/rules.py
vero_sdk/strategy/__init__.py
vero_sdk/strategy/base.cpython-39-x86_64-linux-gnu.so
vero_sdk/strategy/base.py
vero_sdk/strategy/context.cpython-39-x86_64-linux-gnu.so
vero_sdk/strategy/context.py
vero_sdk/strategy/position.cpython-39-x86_64-linux-gnu.so
vero_sdk/strategy/position.py
vero_sdk/strategy/symbol.cpython-39-x86_64-linux-gnu.so
vero_sdk/strategy/symbol.py
vero_sdk/types/__init__.py
vero_sdk/types/account.cpython-39-x86_64-linux-gnu.so
vero_sdk/types/account.py
vero_sdk/types/enums.cpython-39-x86_64-linux-gnu.so
vero_sdk/types/enums.py
vero_algo_sdk-1.0.0.dist-info/METADATA
vero_algo_sdk-1.0.0.dist-info/WHEEL
vero_algo_sdk-1.0.0.dist-info/top_level.txt
vero_algo_sdk-1.0.0.dist-info/RECORD
