Metadata-Version: 2.4
Name: vero-algo-sdk
Version: 1.0.0
Summary: Python SDK for Vero Algo trading platform
Author: Vero
Classifier: Development Status :: 3 - Alpha
Classifier: Intended Audience :: Developers
Classifier: License :: OSI Approved :: MIT License
Classifier: Programming Language :: Python :: 3
Classifier: Programming Language :: Python :: 3.8
Classifier: Programming Language :: Python :: 3.9
Classifier: Programming Language :: Python :: 3.10
Classifier: Programming Language :: Python :: 3.11
Requires-Python: >=3.8
Requires-Dist: requests>=2.25.0
Requires-Dist: websocket-client>=1.0.0
Requires-Dist: python-dateutil>=2.8.0
Requires-Dist: centrifuge-python>=0.1.0
Requires-Dist: backtrader>=1.9.78.123
Requires-Dist: talipp>=1.0.0
Provides-Extra: dev
Requires-Dist: pytest>=7.0.0; extra == "dev"
Requires-Dist: pytest-asyncio>=0.20.0; extra == "dev"
Requires-Dist: Cython>=0.29.0; extra == "dev"
Dynamic: author
Dynamic: classifier
Dynamic: provides-extra
Dynamic: requires-dist
Dynamic: requires-python
Dynamic: summary
